viswaternet/__init__.py
viswaternet/drawing/__init__.py
viswaternet/drawing/animate.py
viswaternet/drawing/base.py
viswaternet/drawing/continuous.py
viswaternet/drawing/discrete.py
viswaternet/drawing/style.py
viswaternet/drawing/unique.py
viswaternet/network/__init__.py
viswaternet/network/initialize.py
viswaternet/network/processing.py
viswaternet/utils/__init__.py
viswaternet/utils/convert_excel.py
viswaternet/utils/fancyarrowpatch_to_linecollection.py
viswaternet/utils/label_generator.py
viswaternet/utils/markers.py
viswaternet/utils/normalize_parameter.py
viswaternet/utils/save_fig.py
viswaternet/utils/unit_conversion.py
viswaternet-2.2.3.dist-info/AUTHORS.rst
viswaternet-2.2.3.dist-info/LICENSE
viswaternet-2.2.3.dist-info/METADATA
viswaternet-2.2.3.dist-info/WHEEL
viswaternet-2.2.3.dist-info/top_level.txt
viswaternet-2.2.3.dist-info/RECORD
