Metadata-Version: 2.1
Name: viswaternet
Version: 2.2.3
Summary: A python package for easy generation and customization of water network graphs.
Home-page: https://github.com/tylertrimble/viswaternet
Author: Tyler Trimble
Author-email: TylerL.Trimble@gmail.com
License: MIT license
Keywords: viswaternet
Classifier: Development Status :: 5 - Production/Stable
Classifier: Intended Audience :: Developers
Classifier: License :: OSI Approved :: MIT License
Classifier: Natural Language :: English
Classifier: Programming Language :: Python :: 3.8
Classifier: Programming Language :: Python :: 3.9
Classifier: Programming Language :: Python :: 3.10
Classifier: Programming Language :: Python :: 3.11
Classifier: Programming Language :: Python :: 3.12
Requires-Python: >=3.8
License-File: LICENSE
License-File: AUTHORS.rst
Requires-Dist: pandas
Requires-Dist: openpyxl
Requires-Dist: numpy
Requires-Dist: matplotlib>=3.5.0
Requires-Dist: wntr
Requires-Dist: imageio
Requires-Dist: imageio-ffmpeg
Requires-Dist: networkx<=3.3,>=2.7
